{
    "key": "group_6383a29dbee61",
    "title": "Seiten-Template: Rechtliche Seite",
    "fields": [
        {
            "key": "field_6383a2a961c3a",
            "label": "Abschnitte",
            "name": "section",
            "type": "repeater",
            "instructions": "",
            "required": 0,
            "conditional_logic": 0,
            "wrapper": {
                "width": "",
                "class": "",
                "id": ""
            },
            "collapsed": "",
            "min": 1,
            "max": 0,
            "layout": "block",
            "button_label": "Abschnitt hinzufügen",
            "sub_fields": [
                {
                    "key": "field_6383a2b461c3b",
                    "label": "Überschrift",
                    "name": "headline",
                    "type": "text",
                    "instructions": "",
                    "required": 0,
                    "conditional_logic": 0,
                    "wrapper": {
                        "width": "",
                        "class": "",
                        "id": ""
                    },
                    "default_value": "",
                    "placeholder": "",
                    "prepend": "",
                    "append": "",
                    "maxlength": ""
                },
                {
                    "key": "field_6383a3375f3bc",
                    "label": "Blöcke",
                    "name": "blocks",
                    "type": "repeater",
                    "instructions": "",
                    "required": 0,
                    "conditional_logic": 0,
                    "wrapper": {
                        "width": "",
                        "class": "",
                        "id": ""
                    },
                    "collapsed": "",
                    "min": 1,
                    "max": 0,
                    "layout": "block",
                    "button_label": "Block hinzufügen",
                    "sub_fields": [
                        {
                            "key": "field_6383a3485f3bd",
                            "label": "Überschrift",
                            "name": "headline",
                            "type": "textarea",
                            "instructions": "",
                            "required": 1,
                            "conditional_logic": 0,
                            "wrapper": {
                                "width": "",
                                "class": "",
                                "id": ""
                            },
                            "default_value": "",
                            "placeholder": "",
                            "maxlength": "",
                            "rows": 2,
                            "new_lines": "br"
                        },
                        {
                            "key": "field_6383a2ba61c3c",
                            "label": "Text",
                            "name": "text",
                            "type": "wysiwyg",
                            "instructions": "",
                            "required": 0,
                            "conditional_logic": 0,
                            "wrapper": {
                                "width": "",
                                "class": "",
                                "id": ""
                            },
                            "default_value": "",
                            "tabs": "all",
                            "toolbar": "full",
                            "media_upload": 1,
                            "delay": 0
                        }
                    ]
                }
            ]
        }
    ],
    "location": [
        [
            {
                "param": "post_template",
                "operator": "==",
                "value": "page-templates\/legal.php"
            }
        ]
    ],
    "menu_order": 0,
    "position": "normal",
    "style": "seamless",
    "label_placement": "top",
    "instruction_placement": "label",
    "hide_on_screen": "",
    "active": true,
    "description": "",
    "modified": 1669571850
}